[
  {
    "title": "Calendrier des manifestations",
    "description": "Événement à Sierre : Calendrier des manifestations. Consultez le lien source pour plus de détails.",
    "date": "2026-02-10",
    "time": null,
    "end_date": "2026-02-10",
    "end_time": null,
    "location": "Sierre, Valais, Suisse",
    "latitude": 46.2922522,
    "longitude": 7.5323195,
    "categories": [
      "Autre"
    ],
    "source_url": "https://www.sierre.ch/fr/calendrier-manifestations-1738/agenda-viewguidle-1198174308.html",
    "organizer_name": "Ville de Sierre",
    "organizer_email": "",
    "validation_status": "auto_validated"
  },
  {
    "title": "Calendrier des manifestations",
    "description": "Événement à Sierre : Calendrier des manifestations. Consultez le lien source pour plus de détails.",
    "date": "2026-02-13",
    "time": null,
    "end_date": "2026-02-13",
    "end_time": null,
    "location": "Les Caves de Courten, Rue du Bourg 30, 3960 Sierre",
    "latitude": 46.2909697,
    "longitude": 7.530875,
    "categories": [
      "Autre"
    ],
    "source_url": "https://www.sierre.ch/fr/calendrier-manifestations-1738/agenda-viewguidle-1230898878.html",
    "organizer_name": "Ville de Sierre",
    "organizer_email": "",
    "validation_status": "auto_validated"
  },
  {
    "title": "Calendrier des manifestations",
    "description": "Événement à Sierre : Calendrier des manifestations. Consultez le lien source pour plus de détails.",
    "date": "2026-02-14",
    "time": null,
    "end_date": "2026-02-14",
    "end_time": null,
    "location": "Sierre, Valais, Suisse",
    "latitude": 46.2922522,
    "longitude": 7.5323195,
    "categories": [
      "Autre"
    ],
    "source_url": "https://www.sierre.ch/fr/calendrier-manifestations-1738/agenda-viewguidle-1229477395.html",
    "organizer_name": "Ville de Sierre",
    "organizer_email": "",
    "validation_status": "auto_validated"
  },
  {
    "title": "Calendrier des manifestations",
    "description": "Événement à Sierre : Calendrier des manifestations. Consultez le lien source pour plus de détails.",
    "date": "2026-02-13",
    "time": null,
    "end_date": "2026-02-13",
    "end_time": null,
    "location": "Sierre, Valais, Suisse",
    "latitude": 46.2922522,
    "longitude": 7.5323195,
    "categories": [
      "Autre"
    ],
    "source_url": "https://www.sierre.ch/fr/calendrier-manifestations-1738/agenda-viewguidle-1228498920.html",
    "organizer_name": "Ville de Sierre",
    "organizer_email": "",
    "validation_status": "auto_validated"
  },
  {
    "title": "Calendrier des manifestations",
    "description": "Événement à Sierre : Calendrier des manifestations. Consultez le lien source pour plus de détails.",
    "date": "2026-02-13",
    "time": null,
    "end_date": "2026-02-13",
    "end_time": null,
    "location": "Sierre, Valais, Suisse",
    "latitude": 46.2922522,
    "longitude": 7.5323195,
    "categories": [
      "Autre"
    ],
    "source_url": "https://www.sierre.ch/fr/calendrier-manifestations-1738/agenda-viewguidle-1231350384.html",
    "organizer_name": "Ville de Sierre",
    "organizer_email": "",
    "validation_status": "auto_validated"
  },
  {
    "title": "Calendrier des manifestations",
    "description": "Événement à Sierre : Calendrier des manifestations. Consultez le lien source pour plus de détails.",
    "date": "2026-02-15",
    "time": null,
    "end_date": "2026-02-15",
    "end_time": null,
    "location": "Sierre, Valais, Suisse",
    "latitude": 46.2922522,
    "longitude": 7.5323195,
    "categories": [
      "Autre"
    ],
    "source_url": "https://www.sierre.ch/fr/calendrier-manifestations-1738/agenda-viewguidle-1198174085.html",
    "organizer_name": "Ville de Sierre",
    "organizer_email": "",
    "validation_status": "auto_validated"
  },
  {
    "title": "Calendrier des manifestations",
    "description": "Événement à Sierre : Calendrier des manifestations. Consultez le lien source pour plus de détails.",
    "date": "2026-02-19",
    "time": null,
    "end_date": "2026-02-19",
    "end_time": null,
    "location": "Sierre, Valais, Suisse",
    "latitude": 46.2922522,
    "longitude": 7.5323195,
    "categories": [
      "Autre"
    ],
    "source_url": "https://www.sierre.ch/fr/calendrier-manifestations-1738/agenda-viewguidle-1198173876.html",
    "organizer_name": "Ville de Sierre",
    "organizer_email": "",
    "validation_status": "auto_validated"
  },
  {
    "title": "Calendrier des manifestations",
    "description": "Événement à Sierre : Calendrier des manifestations. Consultez le lien source pour plus de détails.",
    "date": "2026-02-20",
    "time": null,
    "end_date": "2026-02-20",
    "end_time": null,
    "location": "Sierre, Valais, Suisse",
    "latitude": 46.2922522,
    "longitude": 7.5323195,
    "categories": [
      "Autre"
    ],
    "source_url": "https://www.sierre.ch/fr/calendrier-manifestations-1738/agenda-viewguidle-1217935776.html",
    "organizer_name": "Ville de Sierre",
    "organizer_email": "",
    "validation_status": "auto_validated"
  },
  {
    "title": "Calendrier des manifestations",
    "description": "Événement à Sierre : Calendrier des manifestations. Consultez le lien source pour plus de détails.",
    "date": "2026-02-20",
    "time": null,
    "end_date": "2026-02-20",
    "end_time": null,
    "location": "Les Caves de Courten, Rue du Bourg 30, 3960 Sierre",
    "latitude": 46.2909697,
    "longitude": 7.530875,
    "categories": [
      "Autre"
    ],
    "source_url": "https://www.sierre.ch/fr/calendrier-manifestations-1738/agenda-viewguidle-1230898884.html",
    "organizer_name": "Ville de Sierre",
    "organizer_email": "",
    "validation_status": "auto_validated"
  },
  {
    "title": "Calendrier des manifestations",
    "description": "Événement à Sierre : Calendrier des manifestations. Consultez le lien source pour plus de détails.",
    "date": "2026-02-21",
    "time": null,
    "end_date": "2026-02-21",
    "end_time": null,
    "location": "Sierre, Valais, Suisse",
    "latitude": 46.2922522,
    "longitude": 7.5323195,
    "categories": [
      "Autre"
    ],
    "source_url": "https://www.sierre.ch/fr/calendrier-manifestations-1738/agenda-viewguidle-1229143114.html",
    "organizer_name": "Ville de Sierre",
    "organizer_email": "",
    "validation_status": "auto_validated"
  },
  {
    "title": "Calendrier des manifestations",
    "description": "Événement à Sierre : Calendrier des manifestations. Consultez le lien source pour plus de détails.",
    "date": "2026-02-26",
    "time": null,
    "end_date": "2026-02-26",
    "end_time": null,
    "location": "Colline de Daval, 3960 Sierre",
    "latitude": 46.2743358,
    "longitude": 7.5139482,
    "categories": [
      "Autre"
    ],
    "source_url": "https://www.sierre.ch/fr/calendrier-manifestations-1738/agenda-viewguidle-1231561511.html",
    "organizer_name": "Ville de Sierre",
    "organizer_email": "",
    "validation_status": "auto_validated"
  },
  {
    "title": "Calendrier des manifestations",
    "description": "Événement à Sierre : Calendrier des manifestations. Consultez le lien source pour plus de détails.",
    "date": "2026-02-28",
    "time": null,
    "end_date": "2026-02-28",
    "end_time": null,
    "location": "Sierre, Valais, Suisse",
    "latitude": 46.2922522,
    "longitude": 7.5323195,
    "categories": [
      "Autre"
    ],
    "source_url": "https://www.sierre.ch/fr/calendrier-manifestations-1738/agenda-viewguidle-1229383743.html",
    "organizer_name": "Ville de Sierre",
    "organizer_email": "",
    "validation_status": "auto_validated"
  },
  {
    "title": "Calendrier des manifestations",
    "description": "Événement à Sierre : Calendrier des manifestations. Consultez le lien source pour plus de détails.",
    "date": "2026-02-28",
    "time": null,
    "end_date": "2026-02-28",
    "end_time": null,
    "location": "Sierre, Valais, Suisse",
    "latitude": 46.2922522,
    "longitude": 7.5323195,
    "categories": [
      "Autre"
    ],
    "source_url": "https://www.sierre.ch/fr/calendrier-manifestations-1738/agenda-viewguidle-1231350388.html",
    "organizer_name": "Ville de Sierre",
    "organizer_email": "",
    "validation_status": "auto_validated"
  },
  {
    "title": "Calendrier des manifestations",
    "description": "Événement à Sierre : Calendrier des manifestations. Consultez le lien source pour plus de détails.",
    "date": "2026-03-05",
    "time": null,
    "end_date": "2026-03-05",
    "end_time": null,
    "location": "Sierre, Valais, Suisse",
    "latitude": 46.2922522,
    "longitude": 7.5323195,
    "categories": [
      "Autre"
    ],
    "source_url": "https://www.sierre.ch/fr/calendrier-manifestations-1738/agenda-viewguidle-1231561519.html",
    "organizer_name": "Ville de Sierre",
    "organizer_email": "",
    "validation_status": "auto_validated"
  },
  {
    "title": "Calendrier des manifestations",
    "description": "Événement à Sierre : Calendrier des manifestations. Consultez le lien source pour plus de détails.",
    "date": "2026-03-06",
    "time": null,
    "end_date": "2026-03-06",
    "end_time": null,
    "location": "Sierre, Valais, Suisse",
    "latitude": 46.2922522,
    "longitude": 7.5323195,
    "categories": [
      "Autre"
    ],
    "source_url": "https://www.sierre.ch/fr/calendrier-manifestations-1738/agenda-viewguidle-1230898876.html",
    "organizer_name": "Ville de Sierre",
    "organizer_email": "",
    "validation_status": "auto_validated"
  },
  {
    "title": "Calendrier des manifestations",
    "description": "Événement à Sierre : Calendrier des manifestations. Consultez le lien source pour plus de détails.",
    "date": "2026-03-07",
    "time": null,
    "end_date": "2026-03-07",
    "end_time": null,
    "location": "Sierre, Valais, Suisse",
    "latitude": 46.2922522,
    "longitude": 7.5323195,
    "categories": [
      "Autre"
    ],
    "source_url": "https://www.sierre.ch/fr/calendrier-manifestations-1738/agenda-viewguidle-1231506278.html",
    "organizer_name": "Ville de Sierre",
    "organizer_email": "",
    "validation_status": "auto_validated"
  },
  {
    "title": "Calendrier des manifestations",
    "description": "Événement à Sierre : Calendrier des manifestations. Consultez le lien source pour plus de détails.",
    "date": "2026-03-13",
    "time": null,
    "end_date": "2026-03-13",
    "end_time": null,
    "location": "Sierre, Valais, Suisse",
    "latitude": 46.2922522,
    "longitude": 7.5323195,
    "categories": [
      "Autre"
    ],
    "source_url": "https://www.sierre.ch/fr/calendrier-manifestations-1738/agenda-viewguidle-1217935671.html",
    "organizer_name": "Ville de Sierre",
    "organizer_email": "",
    "validation_status": "auto_validated"
  },
  {
    "title": "Calendrier des manifestations",
    "description": "Événement à Sierre : Calendrier des manifestations. Consultez le lien source pour plus de détails.",
    "date": "2026-02-13",
    "time": null,
    "end_date": "2026-02-13",
    "end_time": null,
    "location": "Sierre, Valais, Suisse",
    "latitude": 46.2922522,
    "longitude": 7.5323195,
    "categories": [
      "Autre"
    ],
    "source_url": "https://www.sierre.ch/fr/calendrier-manifestations-1738/agenda-viewguidle-1230898879.html",
    "organizer_name": "Ville de Sierre",
    "organizer_email": "",
    "validation_status": "auto_validated"
  },
  {
    "title": "Calendrier des manifestations",
    "description": "Événement à Sierre : Calendrier des manifestations. Consultez le lien source pour plus de détails.",
    "date": "2026-03-16",
    "time": null,
    "end_date": "2026-03-16",
    "end_time": null,
    "location": "Sierre, Valais, Suisse",
    "latitude": 46.2922522,
    "longitude": 7.5323195,
    "categories": [
      "Autre"
    ],
    "source_url": "https://www.sierre.ch/fr/calendrier-manifestations-1738/agenda-viewguidle-1146882929.html",
    "organizer_name": "Ville de Sierre",
    "organizer_email": "",
    "validation_status": "auto_validated"
  },
  {
    "title": "Calendrier des manifestations",
    "description": "Événement à Sierre : Calendrier des manifestations. Consultez le lien source pour plus de détails.",
    "date": "2026-02-13",
    "time": null,
    "end_date": "2026-02-13",
    "end_time": null,
    "location": "Sierre, Valais, Suisse",
    "latitude": 46.2922522,
    "longitude": 7.5323195,
    "categories": [
      "Autre"
    ],
    "source_url": "https://www.sierre.ch/fr/calendrier-manifestations-1738/agenda-viewguidle-1230859399.html",
    "organizer_name": "Ville de Sierre",
    "organizer_email": "",
    "validation_status": "auto_validated"
  },
  {
    "title": "Calendrier des manifestations",
    "description": "Événement à Sierre : Calendrier des manifestations. Consultez le lien source pour plus de détails.",
    "date": "2026-03-22",
    "time": null,
    "end_date": "2026-03-22",
    "end_time": null,
    "location": "Sierre, Valais, Suisse",
    "latitude": 46.2922522,
    "longitude": 7.5323195,
    "categories": [
      "Autre"
    ],
    "source_url": "https://www.sierre.ch/fr/calendrier-manifestations-1738/agenda-viewguidle-1078836853.html",
    "organizer_name": "Ville de Sierre",
    "organizer_email": "",
    "validation_status": "auto_validated"
  },
  {
    "title": "Calendrier des manifestations",
    "description": "Événement à Sierre : Calendrier des manifestations. Consultez le lien source pour plus de détails.",
    "date": "2026-03-28",
    "time": null,
    "end_date": "2026-03-28",
    "end_time": null,
    "location": "Sierre, Valais, Suisse",
    "latitude": 46.2922522,
    "longitude": 7.5323195,
    "categories": [
      "Autre"
    ],
    "source_url": "https://www.sierre.ch/fr/calendrier-manifestations-1738/agenda-viewguidle-1208104048.html",
    "organizer_name": "Ville de Sierre",
    "organizer_email": "",
    "validation_status": "auto_validated"
  },
  {
    "title": "Calendrier des manifestations",
    "description": "Événement à Sierre : Calendrier des manifestations. Consultez le lien source pour plus de détails.",
    "date": "2026-04-25",
    "time": null,
    "end_date": "2026-04-25",
    "end_time": null,
    "location": "Colline de Daval, 3960 Sierre",
    "latitude": 46.2743358,
    "longitude": 7.5139482,
    "categories": [
      "Autre"
    ],
    "source_url": "https://www.sierre.ch/fr/calendrier-manifestations-1738/agenda-viewguidle-1231561544.html",
    "organizer_name": "Ville de Sierre",
    "organizer_email": "",
    "validation_status": "auto_validated"
  },
  {
    "title": "Calendrier des manifestations",
    "description": "Événement à Sierre : Calendrier des manifestations. Consultez le lien source pour plus de détails.",
    "date": "2026-04-25",
    "time": null,
    "end_date": "2026-04-25",
    "end_time": null,
    "location": "Sierre, Valais, Suisse",
    "latitude": 46.2922522,
    "longitude": 7.5323195,
    "categories": [
      "Autre"
    ],
    "source_url": "https://www.sierre.ch/fr/calendrier-manifestations-1738/agenda-viewguidle-1230556247.html",
    "organizer_name": "Ville de Sierre",
    "organizer_email": "",
    "validation_status": "auto_validated"
  },
  {
    "title": "Calendrier des manifestations",
    "description": "Événement à Sierre : Calendrier des manifestations. Consultez le lien source pour plus de détails.",
    "date": "2026-10-31",
    "time": null,
    "end_date": "2026-10-31",
    "end_time": null,
    "location": "Sierre, Valais, Suisse",
    "latitude": 46.2922522,
    "longitude": 7.5323195,
    "categories": [
      "Autre"
    ],
    "source_url": "https://www.sierre.ch/fr/calendrier-manifestations-1738/agenda-viewguidle-1229143134.html",
    "organizer_name": "Ville de Sierre",
    "organizer_email": "",
    "validation_status": "auto_validated"
  },
  {
    "title": "Calendrier des manifestations",
    "description": "Événement à Sierre : Calendrier des manifestations. Consultez le lien source pour plus de détails.",
    "date": "2026-04-24",
    "time": null,
    "end_date": "2026-04-24",
    "end_time": null,
    "location": "Sierre, Valais, Suisse",
    "latitude": 46.2922522,
    "longitude": 7.5323195,
    "categories": [
      "Autre"
    ],
    "source_url": "https://www.sierre.ch/fr/calendrier-manifestations-1738/agenda-viewguidle-1230898897.html",
    "organizer_name": "Ville de Sierre",
    "organizer_email": "",
    "validation_status": "auto_validated"
  },
  {
    "title": "Calendrier des manifestations",
    "description": "Événement à Sierre : Calendrier des manifestations. Consultez le lien source pour plus de détails.",
    "date": "2026-04-30",
    "time": null,
    "end_date": "2026-04-30",
    "end_time": null,
    "location": "Sierre, Valais, Suisse",
    "latitude": 46.2922522,
    "longitude": 7.5323195,
    "categories": [
      "Autre"
    ],
    "source_url": "https://www.sierre.ch/fr/calendrier-manifestations-1738/agenda-viewguidle-1230898885.html",
    "organizer_name": "Ville de Sierre",
    "organizer_email": "",
    "validation_status": "auto_validated"
  },
  {
    "title": "Calendrier des manifestations",
    "description": "Événement à Sierre : Calendrier des manifestations. Consultez le lien source pour plus de détails.",
    "date": "2026-05-09",
    "time": null,
    "end_date": "2026-05-09",
    "end_time": null,
    "location": "Sierre, Valais, Suisse",
    "latitude": 46.2922522,
    "longitude": 7.5323195,
    "categories": [
      "Autre"
    ],
    "source_url": "https://www.sierre.ch/fr/calendrier-manifestations-1738/agenda-viewguidle-1225997653.html",
    "organizer_name": "Ville de Sierre",
    "organizer_email": "",
    "validation_status": "auto_validated"
  },
  {
    "title": "Calendrier des manifestations",
    "description": "Événement à Sierre : Calendrier des manifestations. Consultez le lien source pour plus de détails.",
    "date": "2026-05-30",
    "time": null,
    "end_date": "2026-05-30",
    "end_time": null,
    "location": "Sierre, Valais, Suisse",
    "latitude": 46.2922522,
    "longitude": 7.5323195,
    "categories": [
      "Autre"
    ],
    "source_url": "https://www.sierre.ch/fr/calendrier-manifestations-1738/agenda-viewguidle-1230556257.html",
    "organizer_name": "Ville de Sierre",
    "organizer_email": "",
    "validation_status": "auto_validated"
  },
  {
    "title": "Calendrier des manifestations",
    "description": "Événement à Sierre : Calendrier des manifestations. Consultez le lien source pour plus de détails.",
    "date": "2026-05-30",
    "time": null,
    "end_date": "2026-05-30",
    "end_time": null,
    "location": "Sierre, Valais, Suisse",
    "latitude": 46.2922522,
    "longitude": 7.5323195,
    "categories": [
      "Autre"
    ],
    "source_url": "https://www.sierre.ch/fr/calendrier-manifestations-1738/agenda-viewguidle-1231506274.html",
    "organizer_name": "Ville de Sierre",
    "organizer_email": "",
    "validation_status": "auto_validated"
  },
  {
    "title": "Calendrier des manifestations",
    "description": "Événement à Sierre : Calendrier des manifestations. Consultez le lien source pour plus de détails.",
    "date": "2026-06-07",
    "time": null,
    "end_date": "2026-06-07",
    "end_time": null,
    "location": "Sierre, Valais, Suisse",
    "latitude": 46.2922522,
    "longitude": 7.5323195,
    "categories": [
      "Autre"
    ],
    "source_url": "https://www.sierre.ch/fr/calendrier-manifestations-1738/agenda-viewguidle-1229410591.html",
    "organizer_name": "Ville de Sierre",
    "organizer_email": "",
    "validation_status": "auto_validated"
  },
  {
    "title": "Calendrier des manifestations",
    "description": "Événement à Sierre : Calendrier des manifestations. Consultez le lien source pour plus de détails.",
    "date": "2026-06-12",
    "time": null,
    "end_date": "2026-06-12",
    "end_time": null,
    "location": "Sierre, Valais, Suisse",
    "latitude": 46.2922522,
    "longitude": 7.5323195,
    "categories": [
      "Autre"
    ],
    "source_url": "https://www.sierre.ch/fr/calendrier-manifestations-1738/agenda-viewguidle-1217935370.html",
    "organizer_name": "Ville de Sierre",
    "organizer_email": "",
    "validation_status": "auto_validated"
  },
  {
    "title": "Calendrier des manifestations",
    "description": "Événement à Sierre : Calendrier des manifestations. Consultez le lien source pour plus de détails.",
    "date": "2026-06-10",
    "time": null,
    "end_date": "2026-06-10",
    "end_time": null,
    "location": "Sierre, Valais, Suisse",
    "latitude": 46.2922522,
    "longitude": 7.5323195,
    "categories": [
      "Autre"
    ],
    "source_url": "https://www.sierre.ch/fr/calendrier-manifestations-1738/agenda-viewguidle-1229714930.html",
    "organizer_name": "Ville de Sierre",
    "organizer_email": "",
    "validation_status": "auto_validated"
  }
]